[
  {
    "name": " 悠 ",
    "message": "保安先生——！",
    "原文": "守衛さんっ――！",
    "原名": " 悠 "
  },
  {
    "name": "守卫",
    "message": "——来了来了……",
    "原文": "――はいはい……",
    "原名": "守衛"
  },
  {
    "name": " 悠 ",
    "message": "我记得——你很麻烦吧",
    "原文": "確か――面倒クサイこと、いうんだったよな",
    "原名": " 悠 "
  },
  {
    "name": " 悠 ",
    "message": "我记得——只要说出我的名字，应该就可以了",
    "原文": "確か――オレの名前をいうだけで、いいハズだよな",
    "原名": " 悠 "
  },
  {
    "name": " 悠 ",
    "message": "前面有休息室吧？　让我过去",
    "原文": "この先に、楽屋があるんだろう？　通してくれ",
    "原名": " 悠 "
  },
  {
    "name": "守卫",
    "message": "——有什么事吗？",
    "原文": "――どの様な用ですか？",
    "原名": "守衛"
  },
  {
    "name": " 悠 ",
    "message": "我是来见麻宫神绪的……",
    "原文": "麻宮神緒に、会いに来たんだが……",
    "原名": " 悠 "
  },
  {
    "name": "守卫",
    "message": "麻宫小姐还在舞台上哦",
    "原文": "麻宮さんは、まだステージにおりますよ",
    "原名": "守衛"
  },
  {
    "name": " 悠 ",
    "message": "也是啊……来得太早了",
    "原文": "そうだよな……来るのが、早過ぎた",
    "原名": " 悠 "
  },
  {
    "name": " 悠 ",
    "message": "麻宫神绪她——",
    "原文": "麻宮神緒は――",
    "原名": " 悠 "
  },
  {
    "name": "守卫",
    "message": "——音乐会还没结束",
    "原文": "――まだ、コンサートが終っていません",
    "原名": "守衛"
  },
  {
    "name": " 悠 ",
    "message": "所以——她不可能还在休息室里",
    "原文": "だから――まだ、楽屋にいるハズがない",
    "原名": " 悠 "
  },
  {
    "name": " 悠 ",
    "message": "这个我知道。我知道的\n　但是……哈哈……再见！",
    "原文": "それは、分かっているんだ。分かっているんだ\n　　　ケド……ね。ハハハ……チャオ！",
    "原名": " 悠 "
  },
  {
    "message": "『我有东西忘拿了……待会儿再见！』",
    "原文": "『忘れモノがあった……あとで、また会おう！』",
    "原名": ""
  },
  {
    "message": "『早上好。我是R＆B的人——』",
    "原文": "『おはようございます。Ｒ＆Ｂの者ですが――』",
    "原名": ""
  },
  {
    "message": "『我有东西忘拿了……待会儿再见！』",
    "原文": "『忘れモノがあった……あとで、また会おう！』",
    "原名": ""
  },
  {
    "message": "『我叫龙崎悠——』",
    "原文": "『オレ、竜崎　悠といいますが――』",
    "原名": ""
  },
  {
    "message": "『早上好。我是R＆B的人——』",
    "原文": "『おはようございます。Ｒ＆Ｂの者ですが――』",
    "原名": ""
  },
  {
    "message": "『我叫龙崎悠——』",
    "原文": "『オレ、竜崎　悠といいますが――』",
    "原名": ""
  },
  {
    "message": "『有东西忘拿了……待会儿，再见！』",
    "原文": "『忘れモノがあった……あとで、また会おう！』",
    "原名": ""
  },
  {
    "message": "『有东西忘拿了……待会儿，再见！』",
    "原文": "『忘れモノがあった……あとで、また会おう！』",
    "原名": ""
  },
  {
    "message": "『请让我通过』",
    "原文": "『そこを、通してもらうよ』",
    "原名": ""
  },
  {
    "message": "『请让我通过』",
    "原文": "『そこを、通してもらうよ』",
    "原名": ""
  },
  {
    "name": " 悠 ",
    "message": "再见！",
    "原文": "さらばだ！",
    "原名": " 悠 "
  },
  {
    "name": "守卫",
    "message": "——你到底在干什么啊……",
    "原文": "――いったい、何をしているんだか……",
    "原名": "守衛"
  },
  {
    "name": "守卫",
    "message": "请——请通过",
    "原文": "どうぞ――お通り下さい",
    "原名": "守衛"
  },
  {
    "name": "守卫",
    "message": "好的好的……请通过",
    "原文": "はいはい……どうぞ、お通り下さい",
    "原名": "守衛"
  },
  {
    "name": "守卫",
    "message": "——噗，呵呵呵……",
    "原文": "――プッ、クククッ……",
    "原名": "守衛"
  },
  {
    "name": " 悠 ",
    "message": "可恶……有什么好笑的！",
    "原文": "クソッ……笑うこと、ないだろう！",
    "原名": " 悠 "
  },
  {
    "name": " 悠 ",
    "message": "——我家的藤岛叫我来的……",
    "原文": "――ウチの藤島に、呼ばれまして……",
    "原名": " 悠 "
  },
  {
    "name": "守卫",
    "message": "辛苦了",
    "原文": "ご苦労様です",
    "原名": "守衛"
  },
  {
    "name": "守卫",
    "message": "好的——麻宫小姐已经告诉过我了",
    "原文": "はい――麻宮さんから、伺っておりますよ",
    "原名": "守衛"
  }
]